github_docs_index/__init__.py
github_docs_index/config.py
github_docs_index/github_instance.py
github_docs_index/index_document.py
github_docs_index/index_generator.py
github_docs_index/index_link.py
github_docs_index/quick_link.py
github_docs_index/repo_link.py
github_docs_index/runner.py
github_docs_index/version.py
github_docs_index/tests/__init__.py
github_docs_index/tests/test_runner.py
github_docs_index/tests/test_version.py
github_docs_index-0.1.2.dist-info/DESCRIPTION.rst
github_docs_index-0.1.2.dist-info/METADATA
github_docs_index-0.1.2.dist-info/RECORD
github_docs_index-0.1.2.dist-info/WHEEL
github_docs_index-0.1.2.dist-info/entry_points.txt
github_docs_index-0.1.2.dist-info/metadata.json
github_docs_index-0.1.2.dist-info/top_level.txt
