Metadata-Version: 2.0
Name: github-docs-index
Version: 0.1.2
Summary: Generate a single-page index of documentation hosted in one or more GitHub organizations on github.com and/or one or more GitHub Enterprise instances.
Home-page: https://github.com/jantman/github-docs-index
Author: Jason Antman
Author-email: jason@jasonantman.com
License: UNKNOWN
Keywords: github documentation index html docutils
Platform: UNKNOWN
Classifier: Development Status :: 1 - Planning
Classifier: License :: OSI Approved :: GNU Affero General Public License v3 or later (AGPLv3+)
Classifier: Programming Language :: Python
Classifier: Programming Language :: Python :: 2.7
Classifier: Programming Language :: Python :: 3
Classifier: Programming Language :: Python :: 3.4
Classifier: Programming Language :: Python :: 3.5
Classifier: Programming Language :: Python :: 3.6
Classifier: Environment :: Console
Classifier: Intended Audience :: Developers
Classifier: Intended Audience :: Information Technology
Classifier: Intended Audience :: System Administrators
Classifier: Natural Language :: English
Classifier: Operating System :: OS Independent
Classifier: Topic :: Documentation
Requires-Dist: PyYAML (<4.0,>=3.0)
Requires-Dist: github3.py (<2.0.0,>=1.1.0)
